mindbox/__init__.py
mindbox/area.py
area_of_a_shape_2-0.0.1.dist-info/METADATA
area_of_a_shape_2-0.0.1.dist-info/WHEEL
area_of_a_shape_2-0.0.1.dist-info/top_level.txt
area_of_a_shape_2-0.0.1.dist-info/RECORD
